labManager/admin_server.py
labmanager_admin_server-1.0.5.dist-info/METADATA
labmanager_admin_server-1.0.5.dist-info/WHEEL
labmanager_admin_server-1.0.5.dist-info/licenses/LICENSE
labmanager_admin_server-1.0.5.dist-info/RECORD
