Metadata-Version: 2.1
Name: labManager-admin-server
Version: 1.0.5
Summary: System for managing multi-station multi-tenant lab setups - admin server.
Project-URL: Source Code, https://github.com/dcnieho/labManager/tree/master/labManager-admin-server
Author-email: Diederick Niehorster <diederick_c.niehorster@humlab.lu.se>
License-Expression: MIT
License-File: LICENSE
Classifier: Intended Audience :: Science/Research
Classifier: Intended Audience :: System Administrators
Classifier: License :: OSI Approved :: MIT License
Classifier: Operating System :: Microsoft
Classifier: Programming Language :: Python :: 3.10
Classifier: Topic :: Scientific/Engineering
Classifier: Topic :: System :: Software Distribution
Classifier: Topic :: System :: Systems Administration
Classifier: Topic :: Utilities
Requires-Python: >=3.10
Requires-Dist: authlib
Requires-Dist: fastapi
Requires-Dist: httpx
Requires-Dist: labmanager-common==1.0.5
Requires-Dist: ldap3!=2.5.0,!=2.5.2,!=2.6,>=2.5
Requires-Dist: python-dotenv
Requires-Dist: uvicorn[standard]
